atomman/VERSION
atomman/__init__.py
atomman/unitconvert.py
atomman/cluster/BondAngleMap.py
atomman/cluster/__init__.py
atomman/core/Atoms.py
atomman/core/Box.py
atomman/core/ElasticConstants.py
atomman/core/ElasticConstants2.py
atomman/core/NeighborList.py
atomman/core/System.py
atomman/core/__init__.py
atomman/core/displacement.py
atomman/core/dmag.c
atomman/core/dmag.cp310-win_amd64.pyd
atomman/core/dmag.pxd
atomman/core/dmag.pyx
atomman/core/dvect.c
atomman/core/dvect.cp310-win_amd64.pyd
atomman/core/dvect.pxd
atomman/core/dvect.pyx
atomman/core/nlist.c
atomman/core/nlist.cp310-win_amd64.pyd
atomman/core/nlist.pyx
atomman/defect/Boundary.py
atomman/defect/DifferentialDisplacement.py
atomman/defect/FreeSurface.py
atomman/defect/GammaSurface.py
atomman/defect/GrainBoundary.py
atomman/defect/IsotropicVolterraDislocation.py
atomman/defect/SDVPN.py
atomman/defect/StackingFault.py
atomman/defect/Strain.c
atomman/defect/Strain.cp310-win_amd64.pyd
atomman/defect/Strain.cp311-win_amd64.pyd
atomman/defect/Strain.cp37-win_amd64.pyd
atomman/defect/Strain.cp38-win_amd64.pyd
atomman/defect/Strain.cp39-win_amd64.pyd
atomman/defect/Strain.pyx
atomman/defect/Stroh.py
atomman/defect/TiltGrainBoundaryHelper.py
atomman/defect/VolterraDislocation.py
atomman/defect/__init__.py
atomman/defect/differential_displacement.py
atomman/defect/dislocation_array.py
atomman/defect/dislocation_dipole_displacement.py
atomman/defect/dislocation_system_basis.py
atomman/defect/dislocation_system_transform.py
atomman/defect/disregistry.py
atomman/defect/free_surface_basis.py
atomman/defect/generator_tools.py
atomman/defect/nye_tensor.py
atomman/defect/nye_tensor_p.py
atomman/defect/pn_arctan_disldensity.py
atomman/defect/pn_arctan_disregistry.py
atomman/defect/point.py
atomman/defect/slip_vector.c
atomman/defect/slip_vector.cp310-win_amd64.pyd
atomman/defect/slip_vector.cp311-win_amd64.pyd
atomman/defect/slip_vector.cp37-win_amd64.pyd
atomman/defect/slip_vector.cp38-win_amd64.pyd
atomman-1.4.11.dist-info/LICENSE.TXT
atomman-1.4.11.dist-info/METADATA
atomman-1.4.11.dist-info/WHEEL
atomman-1.4.11.dist-info/top_level.txt
atomman-1.4.11.dist-info/RECORD
