Metadata-Version: 2.1
Name: atomman
Version: 1.4.11
Summary: Atomistic Manipulation Toolkit
Home-page: https://github.com/usnistgov/atomman/
Author: Lucas Hale
Author-email: lucas.hale@nist.gov
Keywords: atom,atomic,atomistic,molecular dynamics
Classifier: Development Status :: 5 - Production/Stable
Classifier: Intended Audience :: Science/Research
Classifier: Natural Language :: English
Classifier: Programming Language :: Python :: 3.8
Classifier: Programming Language :: Python :: 3.9
Classifier: Programming Language :: Python :: 3.10
Classifier: Programming Language :: Python :: 3.11
Classifier: Topic :: Scientific/Engineering :: Physics
License-File: LICENSE.TXT
Requires-Dist: xmltodict
Requires-Dist: DataModelDict
Requires-Dist: numericalunits
Requires-Dist: numpy >=1.15
Requires-Dist: matplotlib
Requires-Dist: scipy
Requires-Dist: pandas
Requires-Dist: cython
Requires-Dist: requests
Requires-Dist: toolz
Requires-Dist: potentials >=0.3.8
